muse/__init__.py
muse/utils.py
muse/calcs/__init__.py
muse/calcs/density.py
muse/calcs/utils.py
muse/io/__init__.py
muse/io/mptrj.py
muse/jobs/__init__.py
muse/jobs/slurm.py
muse/plots/__init__.py
muse/plots/density.py
muse/plots/pd.py
muse/plots/volume.py
muse/transforms/__init__.py
muse/transforms/mixture.py
muse_xtal-0.1.1.dist-info/LICENSE
muse_xtal-0.1.1.dist-info/METADATA
muse_xtal-0.1.1.dist-info/WHEEL
muse_xtal-0.1.1.dist-info/top_level.txt
muse_xtal-0.1.1.dist-info/RECORD
