Metadata-Version: 2.1
Name: muse-xtal
Version: 0.1.1
Author-email: Yuan Chiang <cyrusyc@lbl.gov>
License: MIT License
Project-URL: Repo, https://github.com/chiang-yuan/muse
Requires-Python: >=3.10
License-File: LICENSE
Requires-Dist: ase
Requires-Dist: matplotlib
Requires-Dist: numpy
Requires-Dist: mp-api>=0.37.0
Requires-Dist: python-dotenv
